ai_security_toolkit/__init__.py
ai_security_toolkit/run.py
ai_security_toolkit/modules/__init__.py
ai_security_toolkit/modules/backdoor_trigger_attack.py
ai_security_toolkit/modules/fgsm_mobilenet.py
ai_security_toolkit/modules/label_flip_attack.py
ai_security_toolkit/modules/membership_inference_attack.py
ai_security_toolkit/modules/simulate_inversion.py
ai_security_toolkit/modules/steal_model.py
ai_security_toolkit/modules/train_mnist_model.py
ai_security_toolkit/shared/__init__.py
ai_security_toolkit/shared/log_utils.py
ai_security_toolkit-1.1.2.dist-info/METADATA
ai_security_toolkit-1.1.2.dist-info/WHEEL
ai_security_toolkit-1.1.2.dist-info/entry_points.txt
ai_security_toolkit-1.1.2.dist-info/top_level.txt
ai_security_toolkit-1.1.2.dist-info/RECORD
