Metadata-Version: 2.4
Name: ai-security-toolkit
Version: 1.1.2
Summary: A red-team AI security framework with adversarial attack modules
Author: Rishit Goel
License: MIT
Requires-Python: >=3.8
Requires-Dist: tensorflow
Requires-Dist: numpy
Requires-Dist: matplotlib
Requires-Dist: pandas
Requires-Dist: cleverhans
Provides-Extra: tensorflow
Requires-Dist: tensorflow; extra == "tensorflow"
Provides-Extra: cleverhans
Requires-Dist: cleverhans; extra == "cleverhans"
Dynamic: requires-python
